ELMAG_Field_Module/Field.py
ELMAG_Field_Module/__init__.py
ELMAG_Field_Module-0.2.0.dist-info/LICENSE
ELMAG_Field_Module-0.2.0.dist-info/METADATA
ELMAG_Field_Module-0.2.0.dist-info/WHEEL
ELMAG_Field_Module-0.2.0.dist-info/top_level.txt
ELMAG_Field_Module-0.2.0.dist-info/RECORD
